Metadata-Version: 1.0
Name: Ibidas
Version: 0.1.26
Summary: Ibidas is an environment for data handling and exploration, able to cope with different data structures and sources
Home-page: https://trac.nbic.nl/ibidas/
Author: M. Hulsman & J.J.Bot
Author-email: m.hulsman@tudelft.nl
License: LGPLv2.1
Platform: UNKNOWN
